{
  "schemaVersion": 1,
  "id": "trans-rights",
  "version": "${version}",

  "name": "Trans Rights!",
  "description": "trans people are valid uwu",
  "authors": [
    "Austin"
  ],
  "contact": {
    "homepage": "https://github.com/the-forecaster/Trans-Rights",
    "github": "https://github.com/the-forecaster",
    "discord": "Austin the Forecaster#0760"
  },

  "license": "CC0-1.0",
  "icon": "assets/transrights/transpride.png",
  "environment": "*",
  "entrypoints": {
    "main": [
      "me.austin.queer.Main"
    ],
    "client": [
      "me.austin.queer.TransRights"
    ]
  },
  "depends": {
    "minecraft": "1.18.x",
    "java": ">=17"
  },
  "mixins": [
    "transrights.mixins.json"
  ],
  "accessWidener": "transrights.accesswidener"
}
